iprint/__init__.py
iprint/color_conversions.py
iprint/colored_text.py
iprint/conversions.py
iprint/iprint.py
test/__init__.py
test/test_iprint.py
tools/__init__.py
tools/colored_text.py
indent_print-1.2.2.dist-info/LICENSE
indent_print-1.2.2.dist-info/METADATA
indent_print-1.2.2.dist-info/WHEEL
indent_print-1.2.2.dist-info/top_level.txt
indent_print-1.2.2.dist-info/RECORD
