Metadata-Version: 2.1
Name: indent-print
Version: 1.2.2
Summary: library can print better readable code
Home-page: https://github.com/matinprogrammer/IPrint
Author: matin ahmadi
Author-email: matinahmadi.programmer@gmail.com
License: UNKNOWN
Platform: UNKNOWN
Classifier: Programming Language :: Python :: 3
Classifier: License :: OSI Approved :: MIT License
Classifier: Operating System :: OS Independent
Requires-Python: >=3.6
License-File: LICENSE
